odoo/addons/hr_timesheet_task_required/README.rst
odoo/addons/hr_timesheet_task_required/__init__.py
odoo/addons/hr_timesheet_task_required/__manifest__.py
odoo/addons/hr_timesheet_task_required/i18n/de.po
odoo/addons/hr_timesheet_task_required/i18n/es.po
odoo/addons/hr_timesheet_task_required/i18n/fr.po
odoo/addons/hr_timesheet_task_required/i18n/fr_FR.po
odoo/addons/hr_timesheet_task_required/i18n/hr_timesheet_task_required.pot
odoo/addons/hr_timesheet_task_required/i18n/it.po
odoo/addons/hr_timesheet_task_required/i18n/nl.po
odoo/addons/hr_timesheet_task_required/i18n/nl_NL.po
odoo/addons/hr_timesheet_task_required/i18n/pt_BR.po
odoo/addons/hr_timesheet_task_required/models/__init__.py
odoo/addons/hr_timesheet_task_required/models/account_analytic_line.py
odoo/addons/hr_timesheet_task_required/models/project_project.py
odoo/addons/hr_timesheet_task_required/models/res_company.py
odoo/addons/hr_timesheet_task_required/models/res_config_settings.py
odoo/addons/hr_timesheet_task_required/readme/CONFIGURE.rst
odoo/addons/hr_timesheet_task_required/readme/CONTRIBUTORS.rst
odoo/addons/hr_timesheet_task_required/readme/DESCRIPTION.rst
odoo/addons/hr_timesheet_task_required/static/description/icon.png
odoo/addons/hr_timesheet_task_required/static/description/index.html
odoo/addons/hr_timesheet_task_required/tests/__init__.py
odoo/addons/hr_timesheet_task_required/tests/test_hr_timesheet_task_required.py
odoo/addons/hr_timesheet_task_required/views/account_analytic_line.xml
odoo/addons/hr_timesheet_task_required/views/project_project.xml
odoo/addons/hr_timesheet_task_required/views/res_config_settings.xml
odoo14_addon_hr_timesheet_task_required-14.0.1.0.1.dev18.dist-info/METADATA
odoo14_addon_hr_timesheet_task_required-14.0.1.0.1.dev18.dist-info/WHEEL
odoo14_addon_hr_timesheet_task_required-14.0.1.0.1.dev18.dist-info/top_level.txt
odoo14_addon_hr_timesheet_task_required-14.0.1.0.1.dev18.dist-info/RECORD
